[{
  "_id": {
    "$oid": "6405d8f73c964b0c25253e88"
  },{
  "_id": {
    "$oid": "6405d8f73c964b0c25253e89"
  },
  "Name": "Dachshund",
  "min_life_expectancy": "12",
  "max_life_expectancy": "16",
  "max_height_male": "9",
  "max_height_female": "9",
  "max_weight_male": "32",
  "max_weight_female": "32",
  "min_height_male": "8",
  "min_height_female": "8",
  "min_weight_male": "16",
  "min_weight_female": "16",
  "good_with_children": "3",
  "good_with_other_dogs": "4",
  "shedding": "2",
  "grooming": "2",
  "drooling": "2",
  "coat_length": "2",
  "good_with_strangers": "4",
  "playfulness": "4",
  "protectiveness": "4",
  "trainability": "4",
  "energy": "3",
  "barking": "5"
},{
  "_id": {
    "$oid": "6405d8f73c964b0c25253e8a"
  },
  "Name": "Labrador Retriever",
  "min_life_expectancy": "10",
  "max_life_expectancy": "12",
  "max_height_male": "24.5",
  "max_height_female": "24.5",
  "max_weight_male": "80",
  "max_weight_female": "70",
  "min_height_male": "22.5",
  "min_height_female": "22.5",
  "min_weight_male": "65",
  "min_weight_female": "55",
  "good_with_children": "5",
  "good_with_other_dogs": "5",
  "shedding": "4",
  "grooming": "2",
  "drooling": "2",
  "coat_length": "1",
  "good_with_strangers": "5",
  "playfulness": "5",
  "protectiveness": "3",
  "trainability": "5",
  "energy": "5",
  "barking": "3"
},{
  "_id": {
    "$oid": "6405d8f73c964b0c25253e8b"
  },
  "Name": "Great Dane",
  "min_life_expectancy": "7",
  "max_life_expectancy": "10",
  "max_height_male": "32",
  "max_height_female": "32",
  "max_weight_male": "175",
  "max_weight_female": "140",
  "min_height_male": "30",
  "min_height_female": "30",
  "min_weight_male": "140",
  "min_weight_female": "110",
  "good_with_children": "3",
  "good_with_other_dogs": "3",
  "shedding": "3",
  "grooming": "1",
  "drooling": "4",
  "coat_length": "1",
  "good_with_strangers": "3",
  "playfulness": "4",
  "protectiveness": "5",
  "trainability": "3",
  "energy": "4",
  "barking": "3"
},{
  "_id": {
    "$oid": "6405d8f73c964b0c25253e8c"
  },
  "Name": "Boxer",
  "min_life_expectancy": "10",
  "max_life_expectancy": "12",
  "max_height_male": "25",
  "max_height_female": "25",
  "max_weight_male": "80",
  "max_weight_female": "65",
  "min_height_male": "23",
  "min_height_female": "23",
  "min_weight_male": "65",
  "min_weight_female": "50",
  "good_with_children": "5",
  "good_with_other_dogs": "3",
  "shedding": "2",
  "grooming": "2",
  "drooling": "3",
  "coat_length": "1",
  "good_with_strangers": "4",
  "playfulness": "4",
  "protectiveness": "4",
  "trainability": "4",
  "energy": "4",
  "barking": "3"
},{
  "_id": {
    "$oid": "6405d8f73c964b0c25253e8d"
  },
  "Name": "Dalmatian",
  "min_life_expectancy": "11",
  "max_life_expectancy": "13",
  "max_height_male": "24",
  "max_height_female": "24",
  "max_weight_male": "70",
  "max_weight_female": "70",
  "min_height_male": "19",
  "min_height_female": "19",
  "min_weight_male": "45",
  "min_weight_female": "45",
  "good_with_children": "3",
  "good_with_other_dogs": "3",
  "shedding": "4",
  "grooming": "2",
  "drooling": "2",
  "coat_length": "1",
  "good_with_strangers": "4",
  "playfulness": "4",
  "protectiveness": "4",
  "trainability": "4",
  "energy": "4",
  "barking": "3"
},{
  "_id": {
    "$oid": "6405d8f73c964b0c25253e8e"
  },
  "Name": "Poodle (Miniature)",
  "min_life_expectancy": "10",
  "max_life_expectancy": "18",
  "max_height_male": "15",
  "max_height_female": "15",
  "max_weight_male": "15",
  "max_weight_female": "15",
  "min_height_male": "10",
  "min_height_female": "10",
  "min_weight_male": "10",
  "min_weight_female": "10",
  "good_with_children": "5",
  "good_with_other_dogs": "3",
  "shedding": "1",
  "grooming": "4",
  "drooling": "1",
  "coat_length": "1",
  "good_with_strangers": "5",
  "playfulness": "5",
  "protectiveness": "3",
  "trainability": "5",
  "energy": "4",
  "barking": "4"
},{
  "_id": {
    "$oid": "6405d8f73c964b0c25253e8f"
  },
  "Name": "Bullmastiff",
  "min_life_expectancy": "7",
  "max_life_expectancy": "9",
  "max_height_male": "27",
  "max_height_female": "27",
  "max_weight_male": "130",
  "max_weight_female": "120",
  "min_height_male": "25",
  "min_height_female": "25",
  "min_weight_male": "110",
  "min_weight_female": "100",
  "good_with_children": "3",
  "good_with_other_dogs": "3",
  "shedding": "3",
  "grooming": "1",
  "drooling": "3",
  "coat_length": "1",
  "good_with_strangers": "3",
  "playfulness": "3",
  "protectiveness": "5",
  "trainability": "4",
  "energy": "4",
  "barking": "1"
},{
  "_id": {
    "$oid": "6405d8f73c964b0c25253e90"
  },
  "Name": "Beagle",
  "min_life_expectancy": "10",
  "max_life_expectancy": "15",
  "max_height_male": "16",
  "max_height_female": "15",
  "max_weight_male": "20",
  "max_weight_female": "30",
  "min_height_male": "14",
  "min_height_female": "13",
  "min_weight_male": "15",
  "min_weight_female": "20",
  "good_with_children": "5",
  "good_with_other_dogs": "5",
  "shedding": "3",
  "grooming": "2",
  "drooling": "1",
  "coat_length": "1",
  "good_with_strangers": "3",
  "playfulness": "4",
  "protectiveness": "2",
  "trainability": "3",
  "energy": "4",
  "barking": "4"
},{
  "_id": {
    "$oid": "6405d8f73c964b0c25253e91"
  },
  "Name": "Border Collie",
  "min_life_expectancy": "12",
  "max_life_expectancy": "15",
  "max_height_male": "22",
  "max_height_female": "22",
  "max_weight_male": "55",
  "max_weight_female": "55",
  "min_height_male": "19",
  "min_height_female": "19",
  "min_weight_male": "30",
  "min_weight_female": "30",
  "good_with_children": "3",
  "good_with_other_dogs": "3",
  "shedding": "3",
  "grooming": "3",
  "drooling": "1",
  "coat_length": "1",
  "good_with_strangers": "4",
  "playfulness": "5",
  "protectiveness": "3",
  "trainability": "5",
  "energy": "5",
  "barking": "4"
},{
  "_id": {
    "$oid": "6405d8f73c964b0c25253e92"
  },
  "Name": "Siberian Husky",
  "min_life_expectancy": "12",
  "max_life_expectancy": "14",
  "max_height_male": "23.5",
  "max_height_female": "23.5",
  "max_weight_male": "60",
  "max_weight_female": "50",
  "min_height_male": "21",
  "min_height_female": "21",
  "min_weight_male": "45",
  "min_weight_female": "35",
  "good_with_children": "5",
  "good_with_other_dogs": "5",
  "shedding": "4",
  "grooming": "2",
  "drooling": "1",
  "coat_length": "1",
  "good_with_strangers": "5",
  "playfulness": "5",
  "protectiveness": "1",
  "trainability": "3",
  "energy": "5",
  "barking": "5"
},{
  "_id": {
    "$oid": "6405d8f73c964b0c25253e93"
  },
  "Name": "Shih Tzu",
  "min_life_expectancy": "10",
  "max_life_expectancy": "18",
  "max_height_male": "10.5",
  "max_height_female": "10.5",
  "max_weight_male": "16",
  "max_weight_female": "16",
  "min_height_male": "9",
  "min_height_female": "9",
  "min_weight_male": "9",
  "min_weight_female": "9",
  "good_with_children": "5",
  "good_with_other_dogs": "5",
  "shedding": "1",
  "grooming": "4",
  "drooling": "1",
  "coat_length": "1",
  "good_with_strangers": "3",
  "playfulness": "3",
  "protectiveness": "3",
  "trainability": "4",
  "energy": "3",
  "barking": "3"
},{
  "_id": {
    "$oid": "6405d8f73c964b0c25253e94"
  },
  "Name": "Pomeranian",
  "min_life_expectancy": "12",
  "max_life_expectancy": "16",
  "max_height_male": "7",
  "max_height_female": "7",
  "max_weight_male": "7",
  "max_weight_female": "7",
  "min_height_male": "6",
  "min_height_female": "6",
  "min_weight_male": "3",
  "min_weight_female": "3",
  "good_with_children": "3",
  "good_with_other_dogs": "3",
  "shedding": "2",
  "grooming": "3",
  "drooling": "1",
  "coat_length": "1",
  "good_with_strangers": "3",
  "playfulness": "3",
  "protectiveness": "4",
  "trainability": "3",
  "energy": "3",
  "barking": "4"
},{
  "_id": {
    "$oid": "6405d8f73c964b0c25253e95"
  },
  "Name": "Cardigan Welsh Corgi",
  "min_life_expectancy": "12",
  "max_life_expectancy": "15",
  "max_height_male": "12.5",
  "max_height_female": "12.5",
  "max_weight_male": "38",
  "max_weight_female": "34",
  "min_height_male": "10.5",
  "min_height_female": "10.5",
  "min_weight_male": "30",
  "min_weight_female": "25",
  "good_with_children": "4",
  "good_with_other_dogs": "3",
  "shedding": "3",
  "grooming": "2",
  "drooling": "1",
  "coat_length": "1",
  "good_with_strangers": "4",
  "playfulness": "4",
  "protectiveness": "3",
  "trainability": "4",
  "energy": "4",
  "barking": "5"
},{
  "_id": {
    "$oid": "6405d8f73c964b0c25253e96"
  },
  "Name": "Greyhound",
  "min_life_expectancy": "10",
  "max_life_expectancy": "13",
  "max_height_male": "30",
  "max_height_female": "30",
  "max_weight_male": "70",
  "max_weight_female": "65",
  "min_height_male": "28",
  "min_height_female": "28",
  "min_weight_male": "65",
  "min_weight_female": "60",
  "good_with_children": "3",
  "good_with_other_dogs": "4",
  "shedding": "2",
  "grooming": "1",
  "drooling": "1",
  "coat_length": "1",
  "good_with_strangers": "3",
  "playfulness": "3",
  "protectiveness": "3",
  "trainability": "3",
  "energy": "4",
  "barking": "3"
},{
  "_id": {
    "$oid": "6405d8f73c964b0c25253e97"
  },
  "Name": "Chow Chow",
  "min_life_expectancy": "8",
  "max_life_expectancy": "12",
  "max_height_male": "20",
  "max_height_female": "20",
  "max_weight_male": "70",
  "max_weight_female": "70",
  "min_height_male": "17",
  "min_height_female": "17",
  "min_weight_male": "45",
  "min_weight_female": "45",
  "good_with_children": "3",
  "good_with_other_dogs": "2",
  "shedding": "3",
  "grooming": "3",
  "drooling": "3",
  "coat_length": "1",
  "good_with_strangers": "2",
  "playfulness": "3",
  "protectiveness": "5",
  "trainability": "3",
  "energy": "3",
  "barking": "1"
},{
  "_id": {
    "$oid": "6405d8f73c964b0c25253e98"
  },
  "Name": "Chinese Shar-Pei",
  "min_life_expectancy": "8",
  "max_life_expectancy": "12",
  "max_height_male": "20",
  "max_height_female": "20",
  "max_weight_male": "60",
  "max_weight_female": "60",
  "min_height_male": "18",
  "min_height_female": "18",
  "min_weight_male": "45",
  "min_weight_female": "45",
  "good_with_children": "3",
  "good_with_other_dogs": "3",
  "shedding": "3",
  "grooming": "1",
  "drooling": "3",
  "coat_length": "1",
  "good_with_strangers": "3",
  "playfulness": "3",
  "protectiveness": "4",
  "trainability": "3",
  "energy": "3",
  "barking": "3"
},{
  "_id": {
    "$oid": "6405d8f73c964b0c25253e99"
  },
  "Name": "Cocker Spaniel",
  "min_life_expectancy": "10",
  "max_life_expectancy": "14",
  "max_height_male": "15.5",
  "max_height_female": "15.5",
  "max_weight_male": "30",
  "max_weight_female": "25",
  "min_height_male": "14.5",
  "min_height_female": "14.5",
  "min_weight_male": "25",
  "min_weight_female": "20",
  "good_with_children": "5",
  "good_with_other_dogs": "5",
  "shedding": "3",
  "grooming": "4",
  "drooling": "2",
  "coat_length": "1",
  "good_with_strangers": "4",
  "playfulness": "3",
  "protectiveness": "3",
  "trainability": "4",
  "energy": "4",
  "barking": "3"
},{
  "_id": {
    "$oid": "6405d8f73c964b0c25253e9a"
  },
  "Name": "Great Pyrenees",
  "min_life_expectancy": "10",
  "max_life_expectancy": "12",
  "max_height_male": "32",
  "max_height_female": "32",
  "max_weight_male": "120",
  "max_weight_female": "90",
  "min_height_male": "27",
  "min_height_female": "27",
  "min_weight_male": "110",
  "min_weight_female": "80",
  "good_with_children": "3",
  "good_with_other_dogs": "3",
  "shedding": "3",
  "grooming": "2",
  "drooling": "3",
  "coat_length": "1",
  "good_with_strangers": "3",
  "playfulness": "3",
  "protectiveness": "5",
  "trainability": "3",
  "energy": "3",
  "barking": "3"
},{
  "_id": {
    "$oid": "6405d8f73c964b0c25253e9b"
  },
  "Name": "West Highland White Terrier",
  "min_life_expectancy": "13",
  "max_life_expectancy": "15",
  "max_height_male": "11",
  "max_height_female": "11",
  "max_weight_male": "20",
  "max_weight_female": "20",
  "min_height_male": "11",
  "min_height_female": "11",
  "min_weight_male": "15",
  "min_weight_female": "15",
  "good_with_children": "5",
  "good_with_other_dogs": "3",
  "shedding": "3",
  "grooming": "3",
  "drooling": "1",
  "coat_length": "1",
  "good_with_strangers": "4",
  "playfulness": "5",
  "protectiveness": "5",
  "trainability": "3",
  "energy": "4",
  "barking": "5"
},{
  "_id": {
    "$oid": "6405d8f73c964b0c25253e9c"
  },
  "Name": "Bernese Mountain Dog",
  "min_life_expectancy": "7",
  "max_life_expectancy": "10",
  "max_height_male": "27.5",
  "max_height_female": "27.5",
  "max_weight_male": "115",
  "max_weight_female": "95",
  "min_height_male": "25",
  "min_height_female": "25",
  "min_weight_male": "80",
  "min_weight_female": "70",
  "good_with_children": "5",
  "good_with_other_dogs": "5",
  "shedding": "5",
  "grooming": "3",
  "drooling": "3",
  "coat_length": "1",
  "good_with_strangers": "4",
  "playfulness": "4",
  "protectiveness": "3",
  "trainability": "4",
  "energy": "4",
  "barking": "3"
},{
  "_id": {
    "$oid": "6405d8f73c964b0c25253e9d"
  },
  "Name": "Bull Terrier",
  "min_life_expectancy": "12",
  "max_life_expectancy": "13",
  "max_height_male": "22",
  "max_height_female": "22",
  "max_weight_male": "70",
  "max_weight_female": "70",
  "min_height_male": "21",
  "min_height_female": "21",
  "min_weight_male": "50",
  "min_weight_female": "50",
  "good_with_children": "3",
  "good_with_other_dogs": "1",
  "shedding": "3",
  "grooming": "2",
  "drooling": "1",
  "coat_length": "1",
  "good_with_strangers": "4",
  "playfulness": "4",
  "protectiveness": "3",
  "trainability": "3",
  "energy": "4",
  "barking": "3"
},{
  "_id": {
    "$oid": "6405d8f73c964b0c25253e9e"
  },
  "Name": "Newfoundland",
  "min_life_expectancy": "9",
  "max_life_expectancy": "10",
  "max_height_male": "28",
  "max_height_female": "28",
  "max_weight_male": "150",
  "max_weight_female": "120",
  "min_height_male": "28",
  "min_height_female": "28",
  "min_weight_male": "130",
  "min_weight_female": "100",
  "good_with_children": "5",
  "good_with_other_dogs": "5",
  "shedding": "3",
  "grooming": "2",
  "drooling": "5",
  "coat_length": "1",
  "good_with_strangers": "5",
  "playfulness": "3",
  "protectiveness": "5",
  "trainability": "3",
  "energy": "3",
  "barking": "1"
},{
  "_id": {
    "$oid": "6405d8f73c964b0c25253e9f"
  },
  "Name": "Basset Hound",
  "min_life_expectancy": "12",
  "max_life_expectancy": "13",
  "max_height_male": "15",
  "max_height_female": "14",
  "max_weight_male": "65",
  "max_weight_female": "65",
  "min_height_male": "12",
  "min_height_female": "11",
  "min_weight_male": "40",
  "min_weight_female": "40",
  "good_with_children": "5",
  "good_with_other_dogs": "5",
  "shedding": "2",
  "grooming": "3",
  "drooling": "4",
  "coat_length": "1",
  "good_with_strangers": "3",
  "playfulness": "3",
  "protectiveness": "3",
  "trainability": "3",
  "energy": "2",
  "barking": "4"
},{
  "_id": {
    "$oid": "6405d8f73c964b0c25253ea0"
  },
  "Name": "German Longhaired Pointer",
  "min_life_expectancy": "12",
  "max_life_expectancy": "14",
  "max_height_male": "28",
  "max_height_female": "28",
  "max_weight_male": "80",
  "max_weight_female": "80",
  "min_height_male": "22",
  "min_height_female": "22",
  "min_weight_male": "55",
  "min_weight_female": "55",
  "good_with_children": "5",
  "good_with_other_dogs": "4",
  "shedding": "3",
  "grooming": "1",
  "drooling": "2",
  "coat_length": "1",
  "good_with_strangers": "4",
  "playfulness": "4",
  "protectiveness": "3",
  "trainability": "5",
  "energy": "4",
  "barking": "3"
},{
  "_id": {
    "$oid": "6405d8f73c964b0c25253ea1"
  },
  "Name": "Pug",
  "min_life_expectancy": "13",
  "max_life_expectancy": "15",
  "max_height_male": "13",
  "max_height_female": "13",
  "max_weight_male": "18",
  "max_weight_female": "18",
  "min_height_male": "10",
  "min_height_female": "10",
  "min_weight_male": "14",
  "min_weight_female": "14",
  "good_with_children": "5",
  "good_with_other_dogs": "4",
  "shedding": "4",
  "grooming": "2",
  "drooling": "1",
  "coat_length": "1",
  "good_with_strangers": "5",
  "playfulness": "5",
  "protectiveness": "3",
  "trainability": "4",
  "energy": "3",
  "barking": "1"
},{
  "_id": {
    "$oid": "6405d8f73c964b0c25253ea2"
  },
  "Name": "Boston Terrier",
  "min_life_expectancy": "11",
  "max_life_expectancy": "13",
  "max_height_male": "17",
  "max_height_female": "17",
  "max_weight_male": "25",
  "max_weight_female": "25",
  "min_height_male": "15",
  "min_height_female": "15",
  "min_weight_male": "12",
  "min_weight_female": "12",
  "good_with_children": "5",
  "good_with_other_dogs": "4",
  "shedding": "2",
  "grooming": "2",
  "drooling": "1",
  "coat_length": "1",
  "good_with_strangers": "5",
  "playfulness": "5",
  "protectiveness": "3",
  "trainability": "4",
  "energy": "4",
  "barking": "2"
},{
  "_id": {
    "$oid": "6405d8f73c964b0c25253ea3"
  },
  "Name": "Maltese",
  "min_life_expectancy": "12",
  "max_life_expectancy": "15",
  "max_height_male": "9",
  "max_height_female": "9",
  "max_weight_male": "8.8",
  "max_weight_female": "8.8",
  "min_height_male": "7",
  "min_height_female": "7",
  "min_weight_male": "6.6",
  "min_weight_female": "6.6",
  "good_with_children": "3",
  "good_with_other_dogs": "3",
  "shedding": "1",
  "grooming": "4",
  "drooling": "1",
  "coat_length": "1",
  "good_with_strangers": "3",
  "playfulness": "3",
  "protectiveness": "4",
  "trainability": "3",
  "energy": "3",
  "barking": "3"
},{
  "_id": {
    "$oid": "6405d8f73c964b0c25253ea4"
  },
  "Name": "Bichon Frise",
  "min_life_expectancy": "14",
  "max_life_expectancy": "15",
  "max_height_male": "11.5",
  "max_height_female": "11.5",
  "max_weight_male": "18",
  "max_weight_female": "18",
  "min_height_male": "9.5",
  "min_height_female": "9.5",
  "min_weight_male": "12",
  "min_weight_female": "12",
  "good_with_children": "5",
  "good_with_other_dogs": "5",
  "shedding": "1",
  "grooming": "5",
  "drooling": "1",
  "coat_length": "1",
  "good_with_strangers": "5",
  "playfulness": "4",
  "protectiveness": "2",
  "trainability": "4",
  "energy": "4",
  "barking": "3"
},{
  "_id": {
    "$oid": "6405d8f73c964b0c25253ea5"
  },
  "Name": "American Bulldog",
  "min_life_expectancy": "10",
  "max_life_expectancy": "12",
  "max_height_male": "28",
  "max_height_female": "24",
  "max_weight_male": "100",
  "max_weight_female": "80",
  "min_height_male": "20",
  "min_height_female": "20",
  "min_weight_male": "75",
  "min_weight_female": "60",
  "good_with_children": "3",
  "good_with_other_dogs": "3",
  "shedding": "2",
  "grooming": "0",
  "drooling": "0",
  "coat_length": "1",
  "good_with_strangers": "0",
  "playfulness": "0",
  "protectiveness": "0",
  "trainability": "4",
  "energy": "0",
  "barking": "1"
},{
  "_id": {
    "$oid": "6405d8f73c964b0c25253ea6"
  },
  "Name": "Chihuahua",
  "min_life_expectancy": "14",
  "max_life_expectancy": "16",
  "max_height_male": "8",
  "max_height_female": "8",
  "max_weight_male": "6",
  "max_weight_female": "6",
  "min_height_male": "5",
  "min_height_female": "5",
  "min_weight_male": "4",
  "min_weight_female": "4",
  "good_with_children": "1",
  "good_with_other_dogs": "3",
  "shedding": "2",
  "grooming": "1",
  "drooling": "1",
  "coat_length": "2",
  "good_with_strangers": "2",
  "playfulness": "4",
  "protectiveness": "4",
  "trainability": "3",
  "energy": "4",
  "barking": "5"
},{
  "_id": {
    "$oid": "6405d8f73c964b0c25253ea7"
  },
  "Name": "Rottweiler",
  "min_life_expectancy": "9",
  "max_life_expectancy": "10",
  "max_height_male": "27",
  "max_height_female": "27",
  "max_weight_male": "135",
  "max_weight_female": "100",
  "min_height_male": "24",
  "min_height_female": "24",
  "min_weight_male": "95",
  "min_weight_female": "80",
  "good_with_children": "3",
  "good_with_other_dogs": "3",
  "shedding": "3",
  "grooming": "1",
  "drooling": "3",
  "coat_length": "1",
  "good_with_strangers": "3",
  "playfulness": "4",
  "protectiveness": "5",
  "trainability": "5",
  "energy": "3",
  "barking": "1"
},{
  "_id": {
    "$oid": "6405d8f73c964b0c25253ea8"
  },
  "Name": "Vizsla",
  "min_life_expectancy": "12",
  "max_life_expectancy": "14",
  "max_height_male": "24",
  "max_height_female": "24",
  "max_weight_male": "60",
  "max_weight_female": "55",
  "min_height_male": "22",
  "min_height_female": "22",
  "min_weight_male": "55",
  "min_weight_female": "44",
  "good_with_children": "5",
  "good_with_other_dogs": "4",
  "shedding": "3",
  "grooming": "2",
  "drooling": "2",
  "coat_length": "1",
  "good_with_strangers": "4",
  "playfulness": "5",
  "protectiveness": "3",
  "trainability": "5",
  "energy": "5",
  "barking": "3"
},{
  "_id": {
    "$oid": "6405d8f73c964b0c25253ea9"
  },
  "Name": "Akita",
  "min_life_expectancy": "10",
  "max_life_expectancy": "14",
  "max_height_male": "28",
  "max_height_female": "28",
  "max_weight_male": "130",
  "max_weight_female": "100",
  "min_height_male": "26",
  "min_height_female": "26",
  "min_weight_male": "100",
  "min_weight_female": "70",
  "good_with_children": "3",
  "good_with_other_dogs": "1",
  "shedding": "3",
  "grooming": "3",
  "drooling": "1",
  "coat_length": "1",
  "good_with_strangers": "2",
  "playfulness": "3",
  "protectiveness": "5",
  "trainability": "3",
  "energy": "4",
  "barking": "2"
},{
  "_id": {
    "$oid": "6405d8f73c964b0c25253eaa"
  },
  "Name": "Shetland Sheepdog",
  "min_life_expectancy": "12",
  "max_life_expectancy": "14",
  "max_height_male": "16",
  "max_height_female": "16",
  "max_weight_male": "25",
  "max_weight_female": "25",
  "min_height_male": "13",
  "min_height_female": "13",
  "min_weight_male": "15",
  "min_weight_female": "15",
  "good_with_children": "5",
  "good_with_other_dogs": "5",
  "shedding": "3",
  "grooming": "3",
  "drooling": "1",
  "coat_length": "1",
  "good_with_strangers": "2",
  "playfulness": "5",
  "protectiveness": "5",
  "trainability": "5",
  "energy": "4",
  "barking": "5"
},{
  "_id": {
    "$oid": "6405d8f73c964b0c25253eab"
  },
  "Name": "Bloodhound",
  "min_life_expectancy": "10",
  "max_life_expectancy": "12",
  "max_height_male": "27",
  "max_height_female": "27",
  "max_weight_male": "110",
  "max_weight_female": "100",
  "min_height_male": "25",
  "min_height_female": "25",
  "min_weight_male": "90",
  "min_weight_female": "80",
  "good_with_children": "3",
  "good_with_other_dogs": "3",
  "shedding": "3",
  "grooming": "2",
  "drooling": "5",
  "coat_length": "1",
  "good_with_strangers": "3",
  "playfulness": "3",
  "protectiveness": "2",
  "trainability": "4",
  "energy": "3",
  "barking": "5"
},{
  "_id": {
    "$oid": "6405d8f73c964b0c25253eac"
  },
  "Name": "Irish Setter",
  "min_life_expectancy": "12",
  "max_life_expectancy": "15",
  "max_height_male": "27",
  "max_height_female": "27",
  "max_weight_male": "70",
  "max_weight_female": "60",
  "min_height_male": "27",
  "min_height_female": "27",
  "min_weight_male": "70",
  "min_weight_female": "60",
  "good_with_children": "5",
  "good_with_other_dogs": "5",
  "shedding": "3",
  "grooming": "3",
  "drooling": "2",
  "coat_length": "1",
  "good_with_strangers": "5",
  "playfulness": "5",
  "protectiveness": "3",
  "trainability": "4",
  "energy": "5",
  "barking": "3"
},{
  "_id": {
    "$oid": "6405d8f73c964b0c25253ead"
  },
  "Name": "Komondor",
  "min_life_expectancy": "10",
  "max_life_expectancy": "12",
  "max_height_male": "30",
  "max_height_female": "27",
  "max_weight_male": "130",
  "max_weight_female": "110",
  "min_height_male": "28",
  "min_height_female": "25",
  "min_weight_male": "110",
  "min_weight_female": "88",
  "good_with_children": "3",
  "good_with_other_dogs": "2",
  "shedding": "1",
  "grooming": "4",
  "drooling": "2",
  "coat_length": "1",
  "good_with_strangers": "3",
  "playfulness": "3",
  "protectiveness": "5",
  "trainability": "4",
  "energy": "3",
  "barking": "3"
},{
  "_id": {
    "$oid": "6405d8f73c964b0c25253eae"
  },
  "Name": "Otterhound",
  "min_life_expectancy": "10",
  "max_life_expectancy": "13",
  "max_height_male": "27",
  "max_height_female": "27",
  "max_weight_male": "115",
  "max_weight_female": "80",
  "min_height_male": "27",
  "min_height_female": "27",
  "min_weight_male": "115",
  "min_weight_female": "80",
  "good_with_children": "3",
  "good_with_other_dogs": "3",
  "shedding": "2",
  "grooming": "2",
  "drooling": "3",
  "coat_length": "1",
  "good_with_strangers": "4",
  "playfulness": "3",
  "protectiveness": "3",
  "trainability": "4",
  "energy": "3",
  "barking": "5"
},{
  "_id": {
    "$oid": "6405d8f73c964b0c25253eaf"
  },
  "Name": "Beauceron",
  "min_life_expectancy": "10",
  "max_life_expectancy": "12",
  "max_height_male": "27.5",
  "max_height_female": "27.5",
  "max_weight_male": "110",
  "max_weight_female": "110",
  "min_height_male": "25.5",
  "min_height_female": "25.5",
  "min_weight_male": "70",
  "min_weight_female": "70",
  "good_with_children": "3",
  "good_with_other_dogs": "3",
  "shedding": "4",
  "grooming": "3",
  "drooling": "1",
  "coat_length": "1",
  "good_with_strangers": "2",
  "playfulness": "3",
  "protectiveness": "4",
  "trainability": "3",
  "energy": "5",
  "barking": "3"
},{
  "_id": {
    "$oid": "6405d8f73c964b0c25253eb0"
  },
  "Name": "Treeing Walker Coonhound",
  "min_life_expectancy": "12",
  "max_life_expectancy": "13",
  "max_height_male": "27",
  "max_height_female": "27",
  "max_weight_male": "70",
  "max_weight_female": "70",
  "min_height_male": "22",
  "min_height_female": "22",
  "min_weight_male": "50",
  "min_weight_female": "50",
  "good_with_children": "5",
  "good_with_other_dogs": "5",
  "shedding": "3",
  "grooming": "1",
  "drooling": "3",
  "coat_length": "1",
  "good_with_strangers": "3",
  "playfulness": "4",
  "protectiveness": "3",
  "trainability": "5",
  "energy": "5",
  "barking": "4"
},{
  "_id": {
    "$oid": "6405d8f73c964b0c25253eb1"
  },
  "Name": "Giant Schnauzer",
  "min_life_expectancy": "12",
  "max_life_expectancy": "15",
  "max_height_male": "27.5",
  "max_height_female": "27.5",
  "max_weight_male": "85",
  "max_weight_female": "75",
  "min_height_male": "25.5",
  "min_height_female": "25.5",
  "min_weight_male": "60",
  "min_weight_female": "55",
  "good_with_children": "3",
  "good_with_other_dogs": "3",
  "shedding": "3",
  "grooming": "4",
  "drooling": "2",
  "coat_length": "1",
  "good_with_strangers": "3",
  "playfulness": "4",
  "protectiveness": "5",
  "trainability": "5",
  "energy": "5",
  "barking": "3"
},{
  "_id": {
    "$oid": "6405d8f73c964b0c25253eb2"
  },
  "Name": "Shiba Inu",
  "min_life_expectancy": "13",
  "max_life_expectancy": "16",
  "max_height_male": "16.5",
  "max_height_female": "16.5",
  "max_weight_male": "23",
  "max_weight_female": "17",
  "min_height_male": "14.5",
  "min_height_female": "14.5",
  "min_weight_male": "23",
  "min_weight_female": "17",
  "good_with_children": "3",
  "good_with_other_dogs": "3",
  "shedding": "3",
  "grooming": "2",
  "drooling": "1",
  "coat_length": "1",
  "good_with_strangers": "3",
  "playfulness": "3",
  "protectiveness": "5",
  "trainability": "2",
  "energy": "3",
  "barking": "3"
},{
  "_id": {
    "$oid": "6405d8f73c964b0c25253eb3"
  },
  "Name": "Norfolk Terrier",
  "min_life_expectancy": "12",
  "max_life_expectancy": "16",
  "max_height_male": "10",
  "max_height_female": "10",
  "max_weight_male": "12",
  "max_weight_female": "12",
  "min_height_male": "9",
  "min_height_female": "9",
  "min_weight_male": "11",
  "min_weight_female": "11",
  "good_with_children": "5",
  "good_with_other_dogs": "3",
  "shedding": "3",
  "grooming": "2",
  "drooling": "1",
  "coat_length": "1",
  "good_with_strangers": "5",
  "playfulness": "4",
  "protectiveness": "4",
  "trainability": "3",
  "energy": "4",
  "barking": "4"
},{
  "_id": {
    "$oid": "6405d8f73c964b0c25253eb4"
  },
  "Name": "Afghan Hound",
  "min_life_expectancy": "12",
  "max_life_expectancy": "18",
  "max_height_male": "27",
  "max_height_female": "27",
  "max_weight_male": "60",
  "max_weight_female": "60",
  "min_height_male": "25",
  "min_height_female": "25",
  "min_weight_male": "50",
  "min_weight_female": "50",
  "good_with_children": "3",
  "good_with_other_dogs": "3",
  "shedding": "1",
  "grooming": "4",
  "drooling": "1",
  "coat_length": "1",
  "good_with_strangers": "3",
  "playfulness": "3",
  "protectiveness": "3",
  "trainability": "1",
  "energy": "4",
  "barking": "3"
},{
  "_id": {
    "$oid": "6405d8f73c964b0c25253eb5"
  },
  "Name": "Brittany",
  "min_life_expectancy": "12",
  "max_life_expectancy": "14",
  "max_height_male": "20.5",
  "max_height_female": "20.5",
  "max_weight_male": "40",
  "max_weight_female": "40",
  "min_height_male": "17.5",
  "min_height_female": "17.5",
  "min_weight_male": "30",
  "min_weight_female": "30",
  "good_with_children": "4",
  "good_with_other_dogs": "4",
  "shedding": "3",
  "grooming": "3",
  "drooling": "1",
  "coat_length": "1",
  "good_with_strangers": "3",
  "playfulness": "4",
  "protectiveness": "3",
  "trainability": "5",
  "energy": "5",
  "barking": "3"
},{
  "_id": {
    "$oid": "6405d8f73c964b0c25253eb6"
  },
  "Name": "Chinook",
  "min_life_expectancy": "12",
  "max_life_expectancy": "15",
  "max_height_male": "26",
  "max_height_female": "26",
  "max_weight_male": "90",
  "max_weight_female": "65",
  "min_height_male": "24",
  "min_height_female": "24",
  "min_weight_male": "55",
  "min_weight_female": "50",
  "good_with_children": "5",
  "good_with_other_dogs": "5",
  "shedding": "3",
  "grooming": "3",
  "drooling": "1",
  "coat_length": "1",
  "good_with_strangers": "3",
  "playfulness": "3",
  "protectiveness": "4",
  "trainability": "4",
  "energy": "3",
  "barking": "5"
},{
  "_id": {
    "$oid": "6405d8f73c964b0c25253eb7"
  },
  "Name": "Doberman Pinscher",
  "min_life_expectancy": "10",
  "max_life_expectancy": "12",
  "max_height_male": "28",
  "max_height_female": "28",
  "max_weight_male": "100",
  "max_weight_female": "90",
  "min_height_male": "26",
  "min_height_female": "26",
  "min_weight_male": "75",
  "min_weight_female": "60",
  "good_with_children": "5",
  "good_with_other_dogs": "3",
  "shedding": "4",
  "grooming": "1",
  "drooling": "2",
  "coat_length": "1",
  "good_with_strangers": "4",
  "playfulness": "4",
  "protectiveness": "5",
  "trainability": "5",
  "energy": "5",
  "barking": "3"
},{
  "_id": {
    "$oid": "6405d8f73c964b0c25253eb8"
  },
  "Name": "Pekingese",
  "min_life_expectancy": "12",
  "max_life_expectancy": "14",
  "max_height_male": "9",
  "max_height_female": "9",
  "max_weight_male": "14",
  "max_weight_female": "14",
  "min_height_male": "6",
  "min_height_female": "6",
  "min_weight_male": "7",
  "min_weight_female": "7",
  "good_with_children": "3",
  "good_with_other_dogs": "3",
  "shedding": "3",
  "grooming": "3",
  "drooling": "1",
  "coat_length": "1",
  "good_with_strangers": "3",
  "playfulness": "4",
  "protectiveness": "4",
  "trainability": "3",
  "energy": "3",
  "barking": "1"
},{
  "_id": {
    "$oid": "6405d8f73c964b0c25253eb9"
  },
  "Name": "Whippet",
  "min_life_expectancy": "12",
  "max_life_expectancy": "15",
  "max_height_male": "22",
  "max_height_female": "22",
  "max_weight_male": "40",
  "max_weight_female": "40",
  "min_height_male": "19",
  "min_height_female": "19",
  "min_weight_male": "25",
  "min_weight_female": "25",
  "good_with_children": "5",
  "good_with_other_dogs": "5",
  "shedding": "2",
  "grooming": "1",
  "drooling": "1",
  "coat_length": "1",
  "good_with_strangers": "3",
  "playfulness": "4",
  "protectiveness": "3",
  "trainability": "3",
  "energy": "4",
  "barking": "1"
},{
  "_id": {
    "$oid": "6405d8f73c964b0c25253eba"
  },
  "Name": "Basenji",
  "min_life_expectancy": "13",
  "max_life_expectancy": "14",
  "max_height_male": "17",
  "max_height_female": "17",
  "max_weight_male": "24",
  "max_weight_female": "22",
  "min_height_male": "17",
  "min_height_female": "17",
  "min_weight_male": "24",
  "min_weight_female": "22",
  "good_with_children": "3",
  "good_with_other_dogs": "3",
  "shedding": "2",
  "grooming": "1",
  "drooling": "1",
  "coat_length": "1",
  "good_with_strangers": "3",
  "playfulness": "3",
  "protectiveness": "3",
  "trainability": "2",
  "energy": "4",
  "barking": "1"
},{
  "_id": {
    "$oid": "6405d8f73c964b0c25253ebb"
  },
  "Name": "Bolognese",
  "min_life_expectancy": "12",
  "max_life_expectancy": "14",
  "max_height_male": "12",
  "max_height_female": "12",
  "max_weight_male": "9",
  "max_weight_female": "9",
  "min_height_male": "10",
  "min_height_female": "10",
  "min_weight_male": "5.5",
  "min_weight_female": "5.5",
  "good_with_children": "3",
  "good_with_other_dogs": "3",
  "shedding": "1",
  "grooming": "3",
  "drooling": "1",
  "coat_length": "1",
  "good_with_strangers": "3",
  "playfulness": "4",
  "protectiveness": "2",
  "trainability": "3",
  "energy": "4",
  "barking": "3"
},{
  "_id": {
    "$oid": "6405d8f73c964b0c25253ebc"
  },
  "Name": "Smooth Fox Terrier",
  "min_life_expectancy": "12",
  "max_life_expectancy": "15",
  "max_height_male": "15.5",
  "max_height_female": "15.5",
  "max_weight_male": "18",
  "max_weight_female": "17",
  "min_height_male": "15.5",
  "min_height_female": "15.5",
  "min_weight_male": "18",
  "min_weight_female": "15",
  "good_with_children": "3",
  "good_with_other_dogs": "3",
  "shedding": "3",
  "grooming": "2",
  "drooling": "1",
  "coat_length": "1",
  "good_with_strangers": "3",
  "playfulness": "4",
  "protectiveness": "5",
  "trainability": "3",
  "energy": "4",
  "barking": "5"
},{
  "_id": {
    "$oid": "6405d8f73c964b0c25253ebd"
  },
  "Name": "Field Spaniel",
  "min_life_expectancy": "12",
  "max_life_expectancy": "13",
  "max_height_male": "18",
  "max_height_female": "18",
  "max_weight_male": "50",
  "max_weight_female": "50",
  "min_height_male": "18",
  "min_height_female": "18",
  "min_weight_male": "35",
  "min_weight_female": "35",
  "good_with_children": "5",
  "good_with_other_dogs": "4",
  "shedding": "3",
  "grooming": "2",
  "drooling": "2",
  "coat_length": "1",
  "good_with_strangers": "4",
  "playfulness": "3",
  "protectiveness": "3",
  "trainability": "5",
  "energy": "3",
  "barking": "3"
},{
  "_id": {
    "$oid": "6405d8f73c964b0c25253ebe"
  },
  "Name": "Havanese",
  "min_life_expectancy": "14",
  "max_life_expectancy": "16",
  "max_height_male": "11.5",
  "max_height_female": "11.5",
  "max_weight_male": "13",
  "max_weight_female": "13",
  "min_height_male": "8.5",
  "min_height_female": "8.5",
  "min_weight_male": "7",
  "min_weight_female": "7",
  "good_with_children": "5",
  "good_with_other_dogs": "5",
  "shedding": "2",
  "grooming": "3",
  "drooling": "1",
  "coat_length": "1",
  "good_with_strangers": "5",
  "playfulness": "5",
  "protectiveness": "3",
  "trainability": "4",
  "energy": "3",
  "barking": "4"
},{
  "_id": {
    "$oid": "6405d8f73c964b0c25253ebf"
  },
  "Name": "Japanese Chin",
  "min_life_expectancy": "10",
  "max_life_expectancy": "12",
  "max_height_male": "11",
  "max_height_female": "11",
  "max_weight_male": "11",
  "max_weight_female": "11",
  "min_height_male": "8",
  "min_height_female": "8",
  "min_weight_male": "7",
  "min_weight_female": "7",
  "good_with_children": "3",
  "good_with_other_dogs": "5",
  "shedding": "3",
  "grooming": "2",
  "drooling": "1",
  "coat_length": "1",
  "good_with_strangers": "3",
  "playfulness": "3",
  "protectiveness": "3",
  "trainability": "3",
  "energy": "3",
  "barking": "2"
},{
  "_id": {
    "$oid": "6405d8f73c964b0c25253ec0"
  },
  "Name": "Keeshond",
  "min_life_expectancy": "12",
  "max_life_expectancy": "15",
  "max_height_male": "18",
  "max_height_female": "18",
  "max_weight_male": "45",
  "max_weight_female": "45",
  "min_height_male": "18",
  "min_height_female": "18",
  "min_weight_male": "35",
  "min_weight_female": "35",
  "good_with_children": "5",
  "good_with_other_dogs": "5",
  "shedding": "3",
  "grooming": "3",
  "drooling": "2",
  "coat_length": "1",
  "good_with_strangers": "5",
  "playfulness": "5",
  "protectiveness": "5",
  "trainability": "5",
  "energy": "4",
  "barking": "4"
},{
  "_id": {
    "$oid": "6405d8f73c964b0c25253ec1"
  },
  "Name": "American Eskimo Dog",
  "min_life_expectancy": "13",
  "max_life_expectancy": "15",
  "max_height_male": "26",
  "max_height_female": "26",
  "max_weight_male": "65",
  "max_weight_female": "65",
  "min_height_male": "24",
  "min_height_female": "24",
  "min_weight_male": "45",
  "min_weight_female": "45",
  "good_with_children": "5",
  "good_with_other_dogs": "3",
  "shedding": "3",
  "grooming": "3",
  "drooling": "1",
  "coat_length": "1",
  "good_with_strangers": "5",
  "playfulness": "3",
  "protectiveness": "3",
  "trainability": "4",
  "energy": "4",
  "barking": "3"
},{
  "_id": {
    "$oid": "6405d8f73c964b0c25253ec2"
  },
  "Name": "American Hairless Terrier",
  "min_life_expectancy": "14",
  "max_life_expectancy": "16",
  "max_height_male": "16",
  "max_height_female": "16",
  "max_weight_male": "16",
  "max_weight_female": "16",
  "min_height_male": "12",
  "min_height_female": "12",
  "min_weight_male": "12",
  "min_weight_female": "12",
  "good_with_children": "5",
  "good_with_other_dogs": "3",
  "shedding": "1",
  "grooming": "1",
  "drooling": "1",
  "coat_length": "1",
  "good_with_strangers": "3",
  "playfulness": "3",
  "protectiveness": "3",
  "trainability": "5",
  "energy": "3",
  "barking": "3"
},{
  "_id": {
    "$oid": "6405d8f73c964b0c25253ec3"
  },
  "Name": "American Leopard Hound",
  "min_life_expectancy": "12",
  "max_life_expectancy": "15",
  "max_height_male": "27",
  "max_height_female": "27",
  "max_weight_male": "70",
  "max_weight_female": "70",
  "min_height_male": "21",
  "min_height_female": "21",
  "min_weight_male": "45",
  "min_weight_female": "45",
  "good_with_children": "5",
  "good_with_other_dogs": "3",
  "shedding": "3",
  "grooming": "1",
  "drooling": "1",
  "coat_length": "1",
  "good_with_strangers": "3",
  "playfulness": "3",
  "protectiveness": "3",
  "trainability": "3",
  "energy": "4",
  "barking": "3"
},{
  "_id": {
    "$oid": "6405d8f73c964b0c25253ec4"
  },
  "Name": "American Water Spaniel",
  "min_life_expectancy": "10",
  "max_life_expectancy": "14",
  "max_height_male": "18",
  "max_height_female": "18",
  "max_weight_male": "45",
  "max_weight_female": "40",
  "min_height_male": "15",
  "min_height_female": "15",
  "min_weight_male": "30",
  "min_weight_female": "25",
  "good_with_children": "3",
  "good_with_other_dogs": "3",
  "shedding": "1",
  "grooming": "3",
  "drooling": "1",
  "coat_length": "1",
  "good_with_strangers": "3",
  "playfulness": "3",
  "protectiveness": "3",
  "trainability": "5",
  "energy": "3",
  "barking": "3"
},{
  "_id": {
    "$oid": "6405d8f73c964b0c25253ec5"
  },
  "Name": "Anatolian Shepherd Dog",
  "min_life_expectancy": "11",
  "max_life_expectancy": "13",
  "max_height_male": "29",
  "max_height_female": "29",
  "max_weight_male": "150",
  "max_weight_female": "120",
  "min_height_male": "29",
  "min_height_female": "29",
  "min_weight_male": "110",
  "min_weight_female": "80",
  "good_with_children": "3",
  "good_with_other_dogs": "3",
  "shedding": "3",
  "grooming": "2",
  "drooling": "1",
  "coat_length": "1",
  "good_with_strangers": "1",
  "playfulness": "3",
  "protectiveness": "5",
  "trainability": "2",
  "energy": "3",
  "barking": "3"
},{
  "_id": {
    "$oid": "6405d8f73c964b0c25253ec6"
  },
  "Name": "Barbet",
  "min_life_expectancy": "12",
  "max_life_expectancy": "14",
  "max_height_male": "24.5",
  "max_height_female": "24.5",
  "max_weight_male": "65",
  "max_weight_female": "65",
  "min_height_male": "19",
  "min_height_female": "19",
  "min_weight_male": "35",
  "min_weight_female": "35",
  "good_with_children": "5",
  "good_with_other_dogs": "5",
  "shedding": "1",
  "grooming": "3",
  "drooling": "1",
  "coat_length": "2",
  "good_with_strangers": "3",
  "playfulness": "3",
  "protectiveness": "3",
  "trainability": "4",
  "energy": "3",
  "barking": "3"
},{
  "_id": {
    "$oid": "6405d8f73c964b0c25253ec7"
  },
  "Name": "Bergamasco Sheepdog",
  "min_life_expectancy": "13",
  "max_life_expectancy": "15",
  "max_height_male": "23.5",
  "max_height_female": "23.5",
  "max_weight_male": "84",
  "max_weight_female": "71",
  "min_height_male": "23.5",
  "min_height_female": "23.5",
  "min_weight_male": "70",
  "min_weight_female": "57",
  "good_with_children": "3",
  "good_with_other_dogs": "3",
  "shedding": "1",
  "grooming": "1",
  "drooling": "2",
  "coat_length": "1",
  "good_with_strangers": "3",
  "playfulness": "3",
  "protectiveness": "4",
  "trainability": "3",
  "energy": "3",
  "barking": "1"
},{
  "_id": {
    "$oid": "6405d8f73c964b0c25253ec8"
  },
  "Name": "Berger Picard",
  "min_life_expectancy": "12",
  "max_life_expectancy": "13",
  "max_height_male": "25.5",
  "max_height_female": "25.5",
  "max_weight_male": "70",
  "max_weight_female": "70",
  "min_height_male": "23.5",
  "min_height_female": "23.5",
  "min_weight_male": "50",
  "min_weight_female": "50",
  "good_with_children": "3",
  "good_with_other_dogs": "3",
  "shedding": "3",
  "grooming": "1",
  "drooling": "1",
  "coat_length": "1",
  "good_with_strangers": "3",
  "playfulness": "3",
  "protectiveness": "4",
  "trainability": "4",
  "energy": "4",
  "barking": "2"
},{
  "_id": {
    "$oid": "6405d8f73c964b0c25253ec9"
  },
  "Name": "Boerboel",
  "min_life_expectancy": "9",
  "max_life_expectancy": "11",
  "max_height_male": "27",
  "max_height_female": "27",
  "max_weight_male": "200",
  "max_weight_female": "200",
  "min_height_male": "24",
  "min_height_female": "24",
  "min_weight_male": "150",
  "min_weight_female": "150",
  "good_with_children": "4",
  "good_with_other_dogs": "2",
  "shedding": "3",
  "grooming": "2",
  "drooling": "3",
  "coat_length": "1",
  "good_with_strangers": "3",
  "playfulness": "3",
  "protectiveness": "5",
  "trainability": "4",
  "energy": "3",
  "barking": "3"
},{
  "_id": {
    "$oid": "6405d8f73c964b0c25253eca"
  },
  "Name": "Borzoi",
  "min_life_expectancy": "9",
  "max_life_expectancy": "14",
  "max_height_male": "33",
  "max_height_female": "31",
  "max_weight_male": "105",
  "max_weight_female": "85",
  "min_height_male": "30",
  "min_height_female": "27",
  "min_weight_male": "75",
  "min_weight_female": "60",
  "good_with_children": "3",
  "good_with_other_dogs": "3",
  "shedding": "3",
  "grooming": "2",
  "drooling": "1",
  "coat_length": "1",
  "good_with_strangers": "3",
  "playfulness": "3",
  "protectiveness": "3",
  "trainability": "2",
  "energy": "4",
  "barking": "2"
},{
  "_id": {
    "$oid": "6405d8f73c964b0c25253ecb"
  },
  "Name": "Bracco Italiano",
  "min_life_expectancy": "10",
  "max_life_expectancy": "14",
  "max_height_male": "27",
  "max_height_female": "27",
  "max_weight_male": "90",
  "max_weight_female": "90",
  "min_height_male": "21",
  "min_height_female": "21",
  "min_weight_male": "55",
  "min_weight_female": "55",
  "good_with_children": "4",
  "good_with_other_dogs": "4",
  "shedding": "2",
  "grooming": "1",
  "drooling": "2",
  "coat_length": "1",
  "good_with_strangers": "3",
  "playfulness": "3",
  "protectiveness": "3",
  "trainability": "5",
  "energy": "4",
  "barking": "2"
},{
  "_id": {
    "$oid": "6405d8f73c964b0c25253ecc"
  },
  "Name": "Cane Corso",
  "min_life_expectancy": "9",
  "max_life_expectancy": "12",
  "max_height_male": "27.5",
  "max_height_female": "27.5",
  "max_weight_male": "110",
  "max_weight_female": "99",
  "min_height_male": "25",
  "min_height_female": "25",
  "min_weight_male": "99",
  "min_weight_female": "88",
  "good_with_children": "3",
  "good_with_other_dogs": "3",
  "shedding": "2",
  "grooming": "1",
  "drooling": "3",
  "coat_length": "1",
  "good_with_strangers": "3",
  "playfulness": "3",
  "protectiveness": "5",
  "trainability": "4",
  "energy": "4",
  "barking": "3"
},{
  "_id": {
    "$oid": "6405d8f73c964b0c25253ecd"
  },
  "Name": "Coton de Tulear",
  "min_life_expectancy": "15",
  "max_life_expectancy": "19",
  "max_height_male": "11",
  "max_height_female": "11",
  "max_weight_male": "15",
  "max_weight_female": "13",
  "min_height_male": "10",
  "min_height_female": "10",
  "min_weight_male": "9",
  "min_weight_female": "8",
  "good_with_children": "5",
  "good_with_other_dogs": "5",
  "shedding": "2",
  "grooming": "4",
  "drooling": "1",
  "coat_length": "1",
  "good_with_strangers": "5",
  "playfulness": "4",
  "protectiveness": "3",
  "trainability": "4",
  "energy": "3",
  "barking": "1"
},{
  "_id": {
    "$oid": "6405d8f73c964b0c25253ece"
  },
  "Name": "Papillon",
  "min_life_expectancy": "14",
  "max_life_expectancy": "16",
  "max_height_male": "11",
  "max_height_female": "11",
  "max_weight_male": "10",
  "max_weight_female": "10",
  "min_height_male": "8",
  "min_height_female": "8",
  "min_weight_male": "5",
  "min_weight_female": "5",
  "good_with_children": "5",
  "good_with_other_dogs": "3",
  "shedding": "3",
  "grooming": "2",
  "drooling": "1",
  "coat_length": "1",
  "good_with_strangers": "5",
  "playfulness": "5",
  "protectiveness": "4",
  "trainability": "5",
  "energy": "4",
  "barking": "5"
},{
  "_id": {
    "$oid": "6405d8f73c964b0c25253ecf"
  },
  "Name": "Plott Hound",
  "min_life_expectancy": "12",
  "max_life_expectancy": "14",
  "max_height_male": "25",
  "max_height_female": "25",
  "max_weight_male": "60",
  "max_weight_female": "55",
  "min_height_male": "20",
  "min_height_female": "20",
  "min_weight_male": "50",
  "min_weight_female": "40",
  "good_with_children": "0",
  "good_with_other_dogs": "0",
  "shedding": "0",
  "grooming": "0",
  "drooling": "0",
  "coat_length": "0",
  "good_with_strangers": "0",
  "playfulness": "0",
  "protectiveness": "0",
  "trainability": "0",
  "energy": "0",
  "barking": "0"
},{
  "_id": {
    "$oid": "6405d8f73c964b0c25253ed0"
  },
  "Name": "Pumi",
  "min_life_expectancy": "12",
  "max_life_expectancy": "13",
  "max_height_male": "18.5",
  "max_height_female": "18.5",
  "max_weight_male": "29",
  "max_weight_female": "24",
  "min_height_male": "16",
  "min_height_female": "16",
  "min_weight_male": "27",
  "min_weight_female": "22",
  "good_with_children": "3",
  "good_with_other_dogs": "3",
  "shedding": "1",
  "grooming": "2",
  "drooling": "2",
  "coat_length": "1",
  "good_with_strangers": "3",
  "playfulness": "4",
  "protectiveness": "4",
  "trainability": "5",
  "energy": "5",
  "barking": "3"
},{
  "_id": {
    "$oid": "6405d8f73c964b0c25253ed1"
  },
  "Name": "Xoloitzcuintli",
  "min_life_expectancy": "13",
  "max_life_expectancy": "18",
  "max_height_male": "25",
  "max_height_female": "25",
  "max_weight_male": "60",
  "max_weight_female": "60",
  "min_height_male": "19",
  "min_height_female": "19",
  "min_weight_male": "28",
  "min_weight_female": "28",
  "good_with_children": "3",
  "good_with_other_dogs": "3",
  "shedding": "1",
  "grooming": "1",
  "drooling": "1",
  "coat_length": "1",
  "good_with_strangers": "3",
  "playfulness": "4",
  "protectiveness": "3",
  "trainability": "4",
  "energy": "4",
  "barking": "3"
},{
  "_id": {
    "$oid": "6405d8f73c964b0c25253ed2"
  },
  "Name": "Tibetan Mastiff",
  "min_life_expectancy": "10",
  "max_life_expectancy": "12",
  "max_height_male": "30",
  "max_height_female": "28",
  "max_weight_male": "150",
  "max_weight_female": "120",
  "min_height_male": "26",
  "min_height_female": "24",
  "min_weight_male": "90",
  "min_weight_female": "70",
  "good_with_children": "3",
  "good_with_other_dogs": "3",
  "shedding": "4",
  "grooming": "3",
  "drooling": "3",
  "coat_length": "1",
  "good_with_strangers": "1",
  "playfulness": "3",
  "protectiveness": "5",
  "trainability": "3",
  "energy": "3",
  "barking": "3"
},{
  "_id": {
    "$oid": "6405d8f73c964b0c25253ed3"
  },
  "Name": "Samoyed",
  "min_life_expectancy": "12",
  "max_life_expectancy": "14",
  "max_height_male": "23.5",
  "max_height_female": "23.5",
  "max_weight_male": "65",
  "max_weight_female": "50",
  "min_height_male": "21",
  "min_height_female": "21",
  "min_weight_male": "45",
  "min_weight_female": "35",
  "good_with_children": "5",
  "good_with_other_dogs": "3",
  "shedding": "3",
  "grooming": "3",
  "drooling": "1",
  "coat_length": "1",
  "good_with_strangers": "5",
  "playfulness": "5",
  "protectiveness": "4",
  "trainability": "4",
  "energy": "4",
  "barking": "5"
},{
  "_id": {
    "$oid": "6405d8f73c964b0c25253ed4"
  },
  "Name": "Schipperke",
  "min_life_expectancy": "12",
  "max_life_expectancy": "14",
  "max_height_male": "13",
  "max_height_female": "13",
  "max_weight_male": "16",
  "max_weight_female": "16",
  "min_height_male": "11",
  "min_height_female": "11",
  "min_weight_male": "10",
  "min_weight_female": "10",
  "good_with_children": "3",
  "good_with_other_dogs": "3",
  "shedding": "3",
  "grooming": "2",
  "drooling": "1",
  "coat_length": "1",
  "good_with_strangers": "3",
  "playfulness": "4",
  "protectiveness": "5",
  "trainability": "4",
  "energy": "3",
  "barking": "4"
},{
  "_id": {
    "$oid": "6405d8f73c964b0c25253ed5"
  },
  "Name": "Rhodesian Ridgeback",
  "min_life_expectancy": "10",
  "max_life_expectancy": "12",
  "max_height_male": "27",
  "max_height_female": "27",
  "max_weight_male": "85",
  "max_weight_female": "70",
  "min_height_male": "25",
  "min_height_female": "25",
  "min_weight_male": "85",
  "min_weight_female": "70",
  "good_with_children": "5",
  "good_with_other_dogs": "3",
  "shedding": "3",
  "grooming": "2",
  "drooling": "2",
  "coat_length": "1",
  "good_with_strangers": "3",
  "playfulness": "3",
  "protectiveness": "5",
  "trainability": "4",
  "energy": "3",
  "barking": "2"
},{
  "_id": {
    "$oid": "6405d8f73c964b0c25253ed6"
  },
  "Name": "Russian Toy",
  "min_life_expectancy": "12",
  "max_life_expectancy": "14",
  "max_height_male": "11",
  "max_height_female": "11",
  "max_weight_male": "6.6",
  "max_weight_female": "6.6",
  "min_height_male": "8",
  "min_height_female": "8",
  "min_weight_male": "3.3",
  "min_weight_female": "3.3",
  "good_with_children": "3",
  "good_with_other_dogs": "3",
  "shedding": "3",
  "grooming": "2",
  "drooling": "1",
  "coat_length": "1",
  "good_with_strangers": "3",
  "playfulness": "4",
  "protectiveness": "4",
  "trainability": "4",
  "energy": "3",
  "barking": "4"
},{
  "_id": {
    "$oid": "6405d8f73c964b0c25253ed7"
  },
  "Name": "Nova Scotia Duck Tolling Retriever",
  "min_life_expectancy": "12",
  "max_life_expectancy": "14",
  "max_height_male": "21",
  "max_height_female": "21",
  "max_weight_male": "50",
  "max_weight_female": "50",
  "min_height_male": "18",
  "min_height_female": "18",
  "min_weight_male": "35",
  "min_weight_female": "35",
  "good_with_children": "5",
  "good_with_other_dogs": "4",
  "shedding": "3",
  "grooming": "2",
  "drooling": "2",
  "coat_length": "1",
  "good_with_strangers": "3",
  "playfulness": "5",
  "protectiveness": "3",
  "trainability": "5",
  "energy": "5",
  "barking": "2"
},{
  "_id": {
    "$oid": "6405d8f73c964b0c25253ed8"
  },
  "Name": "Mudi",
  "min_life_expectancy": "12",
  "max_life_expectancy": "14",
  "max_height_male": "18.5",
  "max_height_female": "18.5",
  "max_weight_male": "29",
  "max_weight_female": "29",
  "min_height_male": "15",
  "min_height_female": "15",
  "min_weight_male": "18",
  "min_weight_female": "18",
  "good_with_children": "3",
  "good_with_other_dogs": "3",
  "shedding": "2",
  "grooming": "1",
  "drooling": "2",
  "coat_length": "1",
  "good_with_strangers": "3",
  "playfulness": "5",
  "protectiveness": "4",
  "trainability": "5",
  "energy": "5",
  "barking": "4"
},{
  "_id": {
    "$oid": "6405d8f73c964b0c25253ed9"
  },
  "Name": "Alaskan Klee Kai",
  "min_life_expectancy": "13",
  "max_life_expectancy": "16",
  "max_height_male": "28",
  "max_height_female": "28",
  "max_weight_male": "130",
  "max_weight_female": "100",
  "min_height_male": "26",
  "min_height_female": "26",
  "min_weight_male": "100",
  "min_weight_female": "70",
  "good_with_children": "0",
  "good_with_other_dogs": "0",
  "shedding": "3",
  "grooming": "2",
  "drooling": "0",
  "coat_length": "1",
  "good_with_strangers": "0",
  "playfulness": "0",
  "protectiveness": "0",
  "trainability": "3",
  "energy": "4",
  "barking": "0"
},{
  "_id": {
    "$oid": "6405d8f73c964b0c25253eda"
  },
  "Name": "Jindo",
  "min_life_expectancy": "14",
  "max_life_expectancy": "14",
  "max_height_male": "22",
  "max_height_female": "22",
  "max_weight_male": "50",
  "max_weight_female": "50",
  "min_height_male": "18",
  "min_height_female": "18",
  "min_weight_male": "30",
  "min_weight_female": "30",
  "good_with_children": "3",
  "good_with_other_dogs": "3",
  "shedding": "3",
  "grooming": "2",
  "drooling": "1",
  "coat_length": "1",
  "good_with_strangers": "3",
  "playfulness": "3",
  "protectiveness": "5",
  "trainability": "4",
  "energy": "4",
  "barking": "3"
},{
  "_id": {
    "$oid": "6405d8f73c964b0c25253edb"
  },
  "Name": "Irish Terrier",
  "min_life_expectancy": "13",
  "max_life_expectancy": "15",
  "max_height_male": "18",
  "max_height_female": "18",
  "max_weight_male": "27",
  "max_weight_female": "25",
  "min_height_male": "18",
  "min_height_female": "18",
  "min_weight_male": "27",
  "min_weight_female": "25",
  "good_with_children": "5",
  "good_with_other_dogs": "1",
  "shedding": "2",
  "grooming": "1",
  "drooling": "1",
  "coat_length": "1",
  "good_with_strangers": "3",
  "playfulness": "3",
  "protectiveness": "5",
  "trainability": "3",
  "energy": "3",
  "barking": "3"
},{
  "_id": {
    "$oid": "6405d8f73c964b0c25253edc"
  },
  "Name": "Italian Greyhound",
  "min_life_expectancy": "14",
  "max_life_expectancy": "15",
  "max_height_male": "15",
  "max_height_female": "15",
  "max_weight_male": "14",
  "max_weight_female": "14",
  "min_height_male": "13",
  "min_height_female": "13",
  "min_weight_male": "7",
  "min_weight_female": "7",
  "good_with_children": "3",
  "good_with_other_dogs": "5",
  "shedding": "3",
  "grooming": "1",
  "drooling": "1",
  "coat_length": "1",
  "good_with_strangers": "5",
  "playfulness": "4",
  "protectiveness": "3",
  "trainability": "4",
  "energy": "3",
  "barking": "3"
},{
  "_id": {
    "$oid": "6405d8f73c964b0c25253edd"
  },
  "Name": "Hovawart",
  "min_life_expectancy": "10",
  "max_life_expectancy": "14",
  "max_height_male": "28",
  "max_height_female": "28",
  "max_weight_male": "90",
  "max_weight_female": "90",
  "min_height_male": "23",
  "min_height_female": "23",
  "min_weight_male": "65",
  "min_weight_female": "65",
  "good_with_children": "4",
  "good_with_other_dogs": "4",
  "shedding": "3",
  "grooming": "2",
  "drooling": "2",
  "coat_length": "1",
  "good_with_strangers": "4",
  "playfulness": "4",
  "protectiveness": "5",
  "trainability": "4",
  "energy": "3",
  "barking": "1"
},{
  "_id": {
    "$oid": "6405d8f73c964b0c25253ede"
  },
  "Name": "Cavalier King Charles Spaniel",
  "min_life_expectancy": "12",
  "max_life_expectancy": "15",
  "max_height_male": "13",
  "max_height_female": "13",
  "max_weight_male": "18",
  "max_weight_female": "18",
  "min_height_male": "12",
  "min_height_female": "12",
  "min_weight_male": "13",
  "min_weight_female": "13",
  "good_with_children": "5",
  "good_with_other_dogs": "5",
  "shedding": "2",
  "grooming": "2",
  "drooling": "2",
  "coat_length": "1",
  "good_with_strangers": "4",
  "playfulness": "3",
  "protectiveness": "3",
  "trainability": "4",
  "energy": "3",
  "barking": "3"
},{
  "_id": {
    "$oid": "6405d8f73c964b0c25253edf"
  },
  "Name": "Alaskan Malamute",
  "min_life_expectancy": "10",
  "max_life_expectancy": "14",
  "max_height_male": "25",
  "max_height_female": "25",
  "max_weight_male": "85",
  "max_weight_female": "75",
  "min_height_male": "25",
  "min_height_female": "25",
  "min_weight_male": "85",
  "min_weight_female": "75",
  "good_with_children": "3",
  "good_with_other_dogs": "3",
  "shedding": "3",
  "grooming": "3",
  "drooling": "1",
  "coat_length": "1",
  "good_with_strangers": "3",
  "playfulness": "3",
  "protectiveness": "4",
  "trainability": "5",
  "energy": "4",
  "barking": "3"
},{
  "_id": {
    "$oid": "6405d8f73c964b0c25253ee0"
  },
  "Name": "Australian Cattle Dog",
  "min_life_expectancy": "12",
  "max_life_expectancy": "16",
  "max_height_male": "20",
  "max_height_female": "20",
  "max_weight_male": "50",
  "max_weight_female": "50",
  "min_height_male": "18",
  "min_height_female": "18",
  "min_weight_male": "35",
  "min_weight_female": "35",
  "good_with_children": "3",
  "good_with_other_dogs": "3",
  "shedding": "3",
  "grooming": "1",
  "drooling": "1",
  "coat_length": "1",
  "good_with_strangers": "3",
  "playfulness": "3",
  "protectiveness": "4",
  "trainability": "4",
  "energy": "5",
  "barking": "1"
},{
  "_id": {
    "$oid": "6405d8f73c964b0c25253ee1"
  },
  "Name": "Miniature Pinscher",
  "min_life_expectancy": "12",
  "max_life_expectancy": "16",
  "max_height_male": "12.5",
  "max_height_female": "12.5",
  "max_weight_male": "10",
  "max_weight_female": "10",
  "min_height_male": "10",
  "min_height_female": "10",
  "min_weight_male": "8",
  "min_weight_female": "8",
  "good_with_children": "3",
  "good_with_other_dogs": "4",
  "shedding": "3",
  "grooming": "1",
  "drooling": "1",
  "coat_length": "1",
  "good_with_strangers": "3",
  "playfulness": "4",
  "protectiveness": "5",
  "trainability": "3",
  "energy": "5",
  "barking": "5"
},{
  "_id": {
    "$oid": "6405d8f73c964b0c25253ee2"
  },
  "Name": "Belgian Malinois",
  "min_life_expectancy": "14",
  "max_life_expectancy": "16",
  "max_height_male": "26",
  "max_height_female": "26",
  "max_weight_male": "80",
  "max_weight_female": "60",
  "min_height_male": "24",
  "min_height_female": "24",
  "min_weight_male": "60",
  "min_weight_female": "40",
  "good_with_children": "3",
  "good_with_other_dogs": "3",
  "shedding": "3",
  "grooming": "2",
  "drooling": "1",
  "coat_length": "1",
  "good_with_strangers": "3",
  "playfulness": "3",
  "protectiveness": "4",
  "trainability": "5",
  "energy": "4",
  "barking": "3"
},{
  "_id": {
    "$oid": "6405d8f73c964b0c25253ee3"
  },
  "Name": "Staffordshire Bull Terrier",
  "min_life_expectancy": "12",
  "max_life_expectancy": "14",
  "max_height_male": "16",
  "max_height_female": "16",
  "max_weight_male": "38",
  "max_weight_female": "34",
  "min_height_male": "14",
  "min_height_female": "14",
  "min_weight_male": "28",
  "min_weight_female": "24",
  "good_with_children": "5",
  "good_with_other_dogs": "3",
  "shedding": "2",
  "grooming": "2",
  "drooling": "3",
  "coat_length": "1",
  "good_with_strangers": "4",
  "playfulness": "4",
  "protectiveness": "5",
  "trainability": "5",
  "energy": "4",
  "barking": "3"
},{
  "_id": {
    "$oid": "6405d8f73c964b0c25253ee4"
  },
  "Name": "American Staffordshire Terrier",
  "min_life_expectancy": "12",
  "max_life_expectancy": "16",
  "max_height_male": "19",
  "max_height_female": "19",
  "max_weight_male": "70",
  "max_weight_female": "55",
  "min_height_male": "18",
  "min_height_female": "18",
  "min_weight_male": "55",
  "min_weight_female": "40",
  "good_with_children": "3",
  "good_with_other_dogs": "3",
  "shedding": "2",
  "grooming": "1",
  "drooling": "1",
  "coat_length": "1",
  "good_with_strangers": "4",
  "playfulness": "3",
  "protectiveness": "5",
  "trainability": "3",
  "energy": "3",
  "barking": "3"
},{
  "_id": {
    "$oid": "6405d8f73c964b0c25253ee5"
  },
  "Name": "Australian Shepherd",
  "min_life_expectancy": "12",
  "max_life_expectancy": "15",
  "max_height_male": "23",
  "max_height_female": "23",
  "max_weight_male": "65",
  "max_weight_female": "55",
  "min_height_male": "20",
  "min_height_female": "20",
  "min_weight_male": "50",
  "min_weight_female": "40",
  "good_with_children": "5",
  "good_with_other_dogs": "3",
  "shedding": "3",
  "grooming": "2",
  "drooling": "1",
  "coat_length": "1",
  "good_with_strangers": "3",
  "playfulness": "4",
  "protectiveness": "3",
  "trainability": "5",
  "energy": "5",
  "barking": "3"
},{
  "_id": {
    "$oid": "6405d8f73c964b0c25253ee6"
  },
  "Name": "Pembroke Welsh Corgi",
  "min_life_expectancy": "12",
  "max_life_expectancy": "13",
  "max_height_male": "12",
  "max_height_female": "12",
  "max_weight_male": "31",
  "max_weight_female": "28",
  "min_height_male": "10",
  "min_height_female": "10",
  "min_weight_male": "24",
  "min_weight_female": "24",
  "good_with_children": "3",
  "good_with_other_dogs": "4",
  "shedding": "4",
  "grooming": "2",
  "drooling": "1",
  "coat_length": "1",
  "good_with_strangers": "4",
  "playfulness": "4",
  "protectiveness": "5",
  "trainability": "4",
  "energy": "4",
  "barking": "4"
},{
  "_id": {
    "$oid": "6405d8f73c964b0c25253ee7"
  },
  "Name": "Yorkshire Terrier",
  "min_life_expectancy": "11",
  "max_life_expectancy": "15",
  "max_height_male": "8",
  "max_height_female": "8",
  "max_weight_male": "7",
  "max_weight_female": "7",
  "min_height_male": "7",
  "min_height_female": "7",
  "min_weight_male": "7",
  "min_weight_female": "7",
  "good_with_children": "5",
  "good_with_other_dogs": "3",
  "shedding": "1",
  "grooming": "5",
  "drooling": "1",
  "coat_length": "1",
  "good_with_strangers": "5",
  "playfulness": "4",
  "protectiveness": "5",
  "trainability": "4",
  "energy": "4",
  "barking": "4"
},{
  "_id": {
    "$oid": "6405d8f73c964b0c25253ee8"
  },
  "Name": "French Bulldog",
  "min_life_expectancy": "10",
  "max_life_expectancy": "12",
  "max_height_male": "13",
  "max_height_female": "13",
  "max_weight_male": "28",
  "max_weight_female": "26",
  "min_height_male": "11",
  "min_height_female": "11",
  "min_weight_male": "20",
  "min_weight_female": "18",
  "good_with_children": "5",
  "good_with_other_dogs": "4",
  "shedding": "3",
  "grooming": "1",
  "drooling": "3",
  "coat_length": "1",
  "good_with_strangers": "5",
  "playfulness": "5",
  "protectiveness": "3",
  "trainability": "4",
  "energy": "3",
  "barking": "1"
}]